
{
    "1" : { "level" : 1, "award" : 422004}
    ,"2" : { "level" : 2, "award" : 422005}
    ,"3" : { "level" : 3, "award" : 422006}
    ,"4" : { "level" : 10, "award" : 422007}
    ,"5" : { "level" : 20, "award" : 422008}
    ,"6" : { "level" : 50, "award" : 422009}
    ,"7" : { "level" : 100, "award" : 422010}
    ,"8" : { "level" : 200, "award" : 422011}
    ,"9" : { "level" : 500, "award" : 422012}
    ,"10" : { "level" : 1000, "award" : 422013}
    ,"11" : { "level" : -1, "award" : 422014}
}